quru/__init__.py
quru/env.py
quru/quru_logger.py
quru/redis_clt.py
quru/server/__init__.py
quru/server/mq_client.py
quru/server/node_server.py
quru/server/transaction.py
quru/server/protocol/__init__.py
quru/server/protocol/abs_types.py
quru/server/protocol/layer1.py
quru/server/protocol/layer2.py
quru/server/protocol/layer3.py
quru/server/protocol/layer4_actor.py
quru/server/raft/__init__.py
quru/server/raft/abs_types.py
quru/server/raft/core.py
quru/server/raft/list_ledger.py
quru/server/raft/mem_lodge.py
quru/server/raft/timer.py
quru/server/raft/state/__init__.py
quru/server/raft/state/base.py
quru/server/raft/state/candidate.py
quru/server/raft/state/follower.py
quru/server/raft/state/leader.py
quru/server/raft/state/learner.py
quru/words/__init__.py
quru/words/packet.py
quru/words/raft_log.py
quru/words/types.py
quru-0.0.2.dist-info/LICENSE
quru-0.0.2.dist-info/METADATA
quru-0.0.2.dist-info/WHEEL
quru-0.0.2.dist-info/top_level.txt
quru-0.0.2.dist-info/RECORD
