Metadata-Version: 2.1
Name: quru
Version: 0.0.2
Summary: A Python workflow framework
Home-page: https://github.com/ShawnHan1993/quru
Author: Shen Han
License: UNKNOWN
Download-URL: https://github.com/ShawnHan1993/quru/archive/refs/tags/0.0.1.tar.gz
Platform: UNKNOWN
Classifier: Programming Language :: Python :: 3
Classifier: License :: OSI Approved :: MIT License
Classifier: Operating System :: OS Independent
Requires-Python: >=3.7
License-File: LICENSE
Requires-Dist: pika (==1.1.0)
Requires-Dist: mongoengine (==0.23.1)
Requires-Dist: aiozipkin (==0.6.0)
Requires-Dist: aio-pika (==5.6.3)
Requires-Dist: structlog (==20.1.0)
Requires-Dist: redis (==3.2.1)
